Pokechu/__init__.py
Pokechu/pokemon.csv
Pokechu/random_pokemon.py
Pokechu-1.0.0.dist-info/METADATA
Pokechu-1.0.0.dist-info/WHEEL
Pokechu-1.0.0.dist-info/top_level.txt
Pokechu-1.0.0.dist-info/RECORD
