Metadata-Version: 2.1
Name: Pokechu
Version: 1.0.0
Summary: Libreria para generar pokemon aleatorio
Author: Andrew Morales
Author-email: 202224047_morales@tesch.edu.mx
Requires-Dist: pandas
